simpleiniparser/__init__.py
simpleiniparser/simple_iniconfig_parser.py
simpleiniparser/utils.py
simpleiniparser-0.3.0.dist-info/METADATA
simpleiniparser-0.3.0.dist-info/WHEEL
simpleiniparser-0.3.0.dist-info/top_level.txt
simpleiniparser-0.3.0.dist-info/RECORD
