Metadata-Version: 2.1
Name: simpleiniparser
Version: 0.3.0
Summary: Simple tooling to seamlessly parse ini file
Home-page: https://github.com/cgte/simpleiniparser
Author: Colin Goutte
Author-email: colin.goutte@free.fr
License: Apache 2
Keywords: ini utilities
Platform: UNKNOWN
Classifier: Programming Language :: Python :: 2
Classifier: Programming Language :: Python :: 2.7
Classifier: Programming Language :: Python :: 3
Classifier: Programming Language :: Python :: 3.6
Classifier: Programming Language :: Python :: 3.7
Classifier: Programming Language :: Python :: 3.8
Classifier: Intended Audience :: Developers
Classifier: Natural Language :: English
Provides-Extra: dev
Requires-Dist: pytest ; extra == 'dev'
Requires-Dist: pytest-cov ; extra == 'dev'
Requires-Dist: tox ; extra == 'dev'
Requires-Dist: wheel ; extra == 'dev'
